korner/__init__.py
tests/__init__.py
korner-0.0.0.dist-info/LICENSE
korner-0.0.0.dist-info/METADATA
korner-0.0.0.dist-info/WHEEL
korner-0.0.0.dist-info/top_level.txt
korner-0.0.0.dist-info/RECORD
